PyEmailExtracter
