Metadata-Version: 2.1
Name: PyEmailExtracter
Version: 0.6
Summary: Tool for extracting emails from pdf and docx files. (Designed especially for resumes)
Author: Bidut Karki
Author-email: bidutjava3@gmail.com
